tronclass_cli/__init__.py
tronclass_cli/__main__.py
tronclass_cli/api/__init__.py
tronclass_cli/api/auth/__init__.py
tronclass_cli/api/auth/providers.py
tronclass_cli/api/auth/zjuam.py
tronclass_cli/command/__init__.py
tronclass_cli/command/cache.py
tronclass_cli/command/courses.py
tronclass_cli/command/root.py
tronclass_cli/command/todo.py
tronclass_cli/command/activities/__init__.py
tronclass_cli/command/activities/download.py
tronclass_cli/command/activities/list.py
tronclass_cli/command/activities/view.py
tronclass_cli/command/homework/__init__.py
tronclass_cli/command/homework/list.py
tronclass_cli/command/homework/submit.py
tronclass_cli/middleware/__init__.py
tronclass_cli/middleware/api.py
tronclass_cli/middleware/cache.py
tronclass_cli/middleware/config.py
tronclass_cli/middleware/session.py
tronclass_cli/middleware/table.py
tronclass_cli/utils/__init__.py
tronclass_cli/utils/cache.py
tronclass_cli/utils/interact.py
tronclass_cli-0.2.8.dist-info/LICENSE
tronclass_cli-0.2.8.dist-info/METADATA
tronclass_cli-0.2.8.dist-info/WHEEL
tronclass_cli-0.2.8.dist-info/entry_points.txt
tronclass_cli-0.2.8.dist-info/top_level.txt
tronclass_cli-0.2.8.dist-info/RECORD
