Metadata-Version: 2.1
Name: tronclass-cli
Version: 0.2.8
Summary: Command-line interface for Tronclass.
Home-page: https://github.com/HowyoungZhou/tronclass-cli
Author: Howyoung Zhou
Author-email: howyoungzhou@yahoo.com
License: UNKNOWN
Platform: UNKNOWN
Classifier: Programming Language :: Python :: 3
Classifier: License :: OSI Approved :: MIT License
Classifier: Operating System :: OS Independent
Requires-Python: >=3.5
Requires-Dist: tabulate[widechars] (~=0.8.9)
Requires-Dist: keyring (~=22.0.1)
Requires-Dist: requests[security] (~=2.25.1)
Requires-Dist: rsa (~=4.7.1)
Requires-Dist: beautifulsoup4 (~=4.9.3)
Requires-Dist: python-dateutil (~=2.8.1)
Requires-Dist: lxml (~=4.6.2)
Requires-Dist: pyyaml (~=5.4.1)
Requires-Dist: tqdm (~=4.57.0)
Requires-Dist: requests-toolbelt (~=0.9.1)
